solanapy_toolkit/__init__.py
solanapy_toolkit/main.py
solanapy_toolkit/__pycache__/__init__.cpython-311.pyc
solanapy_toolkit/__pycache__/main.cpython-311.pyc
solanapy_toolkit/lib/ClientWrapper.py
solanapy_toolkit/lib/Constants.py
solanapy_toolkit/lib/Helpers.py
solanapy_toolkit/lib/__init__.py
solanapy_toolkit/lib/__pycache__/ClientWrapper.cpython-311.pyc
solanapy_toolkit/lib/__pycache__/Constants.cpython-311.pyc
solanapy_toolkit/lib/__pycache__/Helpers.cpython-311.pyc
solanapy_toolkit/lib/__pycache__/__init__.cpython-311.pyc
solanapy_toolkit-0.0.8.dist-info/LICENSE
solanapy_toolkit-0.0.8.dist-info/METADATA
solanapy_toolkit-0.0.8.dist-info/WHEEL
solanapy_toolkit-0.0.8.dist-info/entry_points.txt
solanapy_toolkit-0.0.8.dist-info/top_level.txt
solanapy_toolkit-0.0.8.dist-info/RECORD
