Metadata-Version: 2.1
Name: solanapy-toolkit
Version: 0.0.8
Summary: Solanapy Toolkit
Home-page: https://codeberg.org/neochine/solanapy-toolkit
Author: Neo Machine
Author-email: neomachine@proton.me
License: GPLv3
Classifier: Programming Language :: Python :: 3
Requires-Python: >=3.7
License-File: LICENSE
Requires-Dist: solana>=0.34.3
Requires-Dist: solders
Requires-Dist: retry
Requires-Dist: base58
